fsspreadsheet/__init__.py
fsspreadsheet/cell.py
fsspreadsheet/cell_type.py
fsspreadsheet/fable_modules/.gitignore
fsspreadsheet/fable_modules/fable_library/__init__.py
fsspreadsheet/fable_modules/fable_library/array_.py
fsspreadsheet/fable_modules/fable_library/async_.py
fsspreadsheet/fable_modules/fable_library/async_builder.py
fsspreadsheet/fable_modules/fable_library/big_int.py
fsspreadsheet/fable_modules/fable_library/bit_converter.py
fsspreadsheet/fable_modules/fable_library/boolean.py
fsspreadsheet/fable_modules/fable_library/char.py
fsspreadsheet/fable_modules/fable_library/choice.py
fsspreadsheet/fable_modules/fable_library/date.py
fsspreadsheet/fable_modules/fable_library/date_offset.py
fsspreadsheet/fable_modules/fable_library/decimal_.py
fsspreadsheet/fable_modules/fable_library/diagnostics.py
fsspreadsheet/fable_modules/fable_library/double.py
fsspreadsheet/fable_modules/fable_library/encoding.py
fsspreadsheet/fable_modules/fable_library/event.py
fsspreadsheet/fable_modules/fable_library/file.py
fsspreadsheet/fable_modules/fable_library/fsharp_collections.py
fsspreadsheet/fable_modules/fable_library/fsharp_core.py
fsspreadsheet/fable_modules/fable_library/global_.py
fsspreadsheet/fable_modules/fable_library/guid.py
fsspreadsheet/fable_modules/fable_library/int32.py
fsspreadsheet/fable_modules/fable_library/list.py
fsspreadsheet/fable_modules/fable_library/long.py
fsspreadsheet/fable_modules/fable_library/mailbox_processor.py
fsspreadsheet/fable_modules/fable_library/map.py
fsspreadsheet/fable_modules/fable_library/map_util.py
fsspreadsheet/fable_modules/fable_library/mutable_map.py
fsspreadsheet/fable_modules/fable_library/mutable_set.py
fsspreadsheet/fable_modules/fable_library/native.py
fsspreadsheet/fable_modules/fable_library/numeric.py
fsspreadsheet/fable_modules/fable_library/observable.py
fsspreadsheet/fable_modules/fable_library/option.py
fsspreadsheet/fable_modules/fable_library/path.py
fsspreadsheet/fable_modules/fable_library/range.py
fsspreadsheet-6.3.1.dist-info/METADATA
fsspreadsheet-6.3.1.dist-info/WHEEL
fsspreadsheet-6.3.1.dist-info/RECORD
