Metadata-Version: 2.1
Name: fsspreadsheet
Version: 6.3.1
Summary: Fable library for Spreadsheet creation and manipulation
Home-page: https://fslab.org/FsSpreadsheet/
License: MIT
Author: Heinrich Lukas Weil
Author-email: hlweil@outlook.de
Maintainer: Oliver Maus
Requires-Python: >=3.11,<4.0
Classifier: License :: OSI Approved :: MIT License
Classifier: Programming Language :: Python :: 3
Classifier: Programming Language :: Python :: 3.11
Classifier: Programming Language :: Python :: 3.12
Requires-Dist: et-xmlfile (>=1.1.0)
Requires-Dist: openpyxl (>=3.1.2)
Project-URL: Documentation, https://fslab.org/FsSpreadsheet/
Project-URL: Repository, https://github.com/fslaborg/FsSpreadsheet
